setup.py
pyimageocr/__init__.py
pyimageocr.egg-info/PKG-INFO
pyimageocr.egg-info/SOURCES.txt
pyimageocr.egg-info/dependency_links.txt
pyimageocr.egg-info/not-zip-safe
pyimageocr.egg-info/top_level.txt