Metadata-Version: 1.0
Name: pyimageocr
Version: 1.0
Summary: Python machine learning ocr.
Home-page: https://github.com/Krprashant94/pyimageocr
Author: Prashant Kumar
Author-email: kr.prashant94@gmail.com
License: MIT
Platform: UNKNOWN
